Maquinas/Ejercicios 1y3/Ejercicios.v
module FFD (input clk, reset, D, output reg Q);
        always @ (posedge clk or posedge reset)begin
            if (reset) begin
                Q <= 1'b0;
            end
            else
                Q <= D;
        end
endmodule


//Salidas

module salidas(input I1, I2, D1, D2, clk, reset, output wire Q, output wire [1:0] Spres, Sfut);
    	wire S0, S1, S2, S0fut, S1fut, S2fut, S3, S3fut, S4, S4fut;

  not W0(NS0,S0);
  not W1(NS1,S1);
  not W2(NS2,S2);
  not W3(NS3,S3);
  not W4(NS4,S4);
  not W5(NI1,I1);
  not W6(NI2,I2);
  not W7(ND1,D1);
  not W8(ND2,D2);

	assign Ng = (NS0 & NS1 & NS2 & NS3 & NS4);

    	assign S0fut = (NI1 & NI2 & ND1 & ND2 & Ng)|(NI1 & NI2 & ND1 & ND2 & S0 & NS1 & NS2 & NS3 & NS4);
    	assign S1fut = (I1 & NI2 & ND1 & ND2 & Ng)|(I1 & NI2 & ND1 & ND2 & NS0 & S1 & NS2 & NS3 & NS4)|(I1 & NI2 & ND1 & ND2 & S0 & NS1 & NS2 & NS3 & NS4);
    	assign S2fut = (NI1 & I2 & ND1 & ND2 & Ng)|(NI1 & I2 & ND1 & ND2 & NS0 & NS1 & S2 & NS3 & NS4)|(NI1 & I2 & ND1 & ND2 & S0 & NS1 & NS2 & NS3 & NS4);
    	assign S3fut = (NI1 & NI2 & D1 & ND2 & Ng)|(NI1 & NI2 & D1 & ND2 & NS0 & NS1 & NS2 & S3 & NS4)|(NI1 & NI2 & D1 & ND2 & S0 & NS1 & NS2 & NS3 & NS4);
    	assign S4fut = (NI1 & NI2 & ND1 & D2 & Ng)|(NI1 & NI2 & ND1 & D2 & NS0 & NS1 & NS2 & NS3 & S4)|(NI1 & NI2 & ND1 & D2 & S0 & NS1 & NS2 & NS3 & NS4);

    	FFD U3(clk, reset, S0fut, S0);
    	FFD U4(clk, reset, S1fut, S1);
    	FFD U5(clk, reset, S2fut, S2);
    	FFD U6(clk, reset, S3fut, S3);
    	FFD U7(clk, reset, S4fut, S4);


	assign Spres = {S4,S3,S2,S1,S0};
	assign Sfut = {S4fut,S3fut,S2fut,S1fut,S0fut};


endmodule

Maquinas/Ejercicios 1y3/Ejercicios_tb.v
//include	"Ejercicios.v"

module testbench();
	
	reg clk, reset, I1,I2,D1,D2;
	wire Q;
	wire [4:0] Sfut, Spres;
	
	salidas al(I1,I2,D1,D2,clk,reset,Q,Sfut,Spres);
	

initial begin
	$display("Salidas");
	$display("Clk | reset | I1 | I2 | D1 | D2 | Sf | S  || |");
	$monitor("  %b  |   %b   | %b | %b | %b | %b | %b | %b || |", clk, reset, I1, I2, D1, D2, Sfut, Spres);
end

initial begin
	clk = 0;
	reset = 0;
	I1 = 0;
	I2 = 0;
	D1 = 0;
	D2 = 0;
	#1 reset = 1;
	#1 reset = 0;
	#10
	I1 = 1;
	I2 = 0;
	D1 = 0;
	D2 = 0;
	#20
	I1 = 0;
	I2 = 1;
	D1 = 0;
	D2 = 0;
	#30
	I1 = 0;
	I2 = 0;
	D1 = 1;
	D2 = 0;
	#40
	I1 = 0;
	I2 = 0;
	D1 = 0;
	D2 = 1;

	
end

initial
	#200 $finish;

	always
	#5 clk = ~clk;

initial begin
	$dumpfile("Ejercicios_tb.vcd");
	$dumpvars(0,testbench);
end
endmodule

Maquinas/Ejercicios 1y3/Ejercicios_tb.vcd
$date
	Sat Oct 17 09:27:11 2020
$end
$version
	Icarus Verilog
$end
$timescale
	1ps
$end
$scope module testbench $end
$var wire 1 ! Q $end
$var wire 5 " Spres [4:0] $end
$var wire 5 # Sfut [4:0] $end
$var reg 1 $ D1 $end
$var reg 1 % D2 $end
$var reg 1 & I1 $end
$var reg 1 ' I2 $end
$var reg 1 ( clk $end
$var reg 1 ) reset $end
$scope module al $end
$var wire 1 $ D1 $end
$var wire 1 % D2 $end
$var wire 1 & I1 $end
$var wire 1 ' I2 $end
$var wire 1 * ND1 $end
$var wire 1 + ND2 $end
$var wire 1 , NI1 $end
$var wire 1 - NI2 $end
$var wire 1 . NS0 $end
$var wire 1 / NS1 $end
$var wire 1 0 NS2 $end
$var wire 1 1 NS3 $end
$var wire 1 2 NS4 $end
$var wire 1 3 Ng $end
$var wire 1 ! Q $end
$var wire 1 4 S0fut $end
$var wire 1 5 S1fut $end
$var wire 1 6 S2fut $end
$var wire 1 7 S3fut $end
$var wire 1 8 S4fut $end
$var wire 1 ( clk $end
$var wire 1 ) reset $end
$var wire 2 9 Spres [1:0] $end
$var wire 2 : Sfut [1:0] $end
$var wire 1 ; S4 $end
$var wire 1 < S3 $end
$var wire 1 = S2 $end
$var wire 1 > S1 $end
$var wire 1 ? S0 $end
$scope module U3 $end
$var wire 1 4 D $end
$var wire 1 ( clk $end
$var wire 1 ) reset $end
$var reg 1 ? Q $end
$upscope $end
$scope module U4 $end
$var wire 1 5 D $end
$var wire 1 ( clk $end
$var wire 1 ) reset $end
$var reg 1 > Q $end
$upscope $end
$scope module U5 $end
$var wire 1 6 D $end
$var wire 1 ( clk $end
$var wire 1 ) reset $end
$var reg 1 = Q $end
$upscope $end
$scope module U6 $end
$var wire 1 7 D $end
$var wire 1 ( clk $end
$var wire 1 ) reset $end
$var reg 1 < Q $end
$upscope $end
$scope module U7 $end
$var wire 1 8 D $end
$var wire 1 ( clk $end
$var wire 1 ) reset $end
$var reg 1 ; Q $end
$upscope $end
$upscope $end
$upscope $end
$enddefinitions $end
#0
$dumpvars
x?
x>
x=
x<
x;
b0x :
bx 9
08
07
06
05
x4
x3
x2
x1
x0
x/
x.
1-
1,
1+
1*
0)
0(
0'
0&
0%
0$
b0xx #
b0x "
z!
$end
#1
b1 "
b1 :
14
13
1.
b0 #
b0 9
1/
10
11
12
0?
0>
0=
0<
0;
1)
#2
0)
#5
03
b1 #
b1 9
0.
1?
1(
#10
0(
#12
04
b10 "
b10 :
15
0,
1&
#15
b10 "
b10 :
15
1.
b10 #
b10 9
0/
0?
1>
1(
#20
0(
#25
1(
#30
0(
#32
b0 "
b0 :
05
0-
1,
1'
0&
#35
16
13
b0 #
b0 9
1/
0>
1(
#40
0(
#45
03
00
1=
1(
#50
0(
#55
1(
#60
0(
#62
06
0*
1-
1$
0'
#65
17
13
10
0=
1(
#70
0(
#75
03
01
1<
1(
#80
0(
#85
1(
#90
0(
#95
1(
#100
0(
#102
07
0+
1*
1%
0$
#105
18
13
11
0<
1(
#110
0(
#115
03
02
1;
1(
